{
  "format_version": "1.21.60",
  "minecraft:geometry": [
    {
      "description": {
        "identifier": "geometry.road_ramp_7_5_part3",
        "texture_width": 16,
        "texture_height": 16,
        "visible_bounds_width": 1,
        "visible_bounds_height": 1,
        "visible_bounds_offset": [
          0,
          0.75,
          0
        ]
      },
      "item_display_transforms": {
        "gui": {
          "rotation": [
            30,
            45,
            0
          ]
        }
      },
      "bones": [
        {
          "name": "block",
          "pivot": [
            0,
            0,
            0
          ],
          "cubes": [
          {"origin": [-8,0,-8],"size": [16,5.344,16]},
          {"origin": [-8,5.344,-8],"size": [16,0.167,15.936]},
          {"origin": [-8,5.511,-8],"size": [16,0.167,14.934]},
          {"origin": [-8,5.678,-8],"size": [16,0.167,13.932]},
          {"origin": [-8,5.845,-8],"size": [16,0.167,12.93]},
          {"origin": [-8,6.012,-8],"size": [16,0.167,11.928]},
          {"origin": [-8,6.179,-8],"size": [16,0.167,10.926]},
          {"origin": [-8,6.346,-8],"size": [16,0.167,9.924]},
          {"origin": [-8,6.513,-8],"size": [16,0.167,8.922]},
          {"origin": [-8,6.68,-8],"size": [16,0.167,7.92]},
          {"origin": [-8,6.847,-8],"size": [16,0.167,6.918]},
          {"origin": [-8,7.014,-8],"size": [16,0.167,5.916]},
          {"origin": [-8,7.181,-8],"size": [16,0.167,4.914]},
          {"origin": [-8,7.348,-8],"size": [16,0.167,3.912]},
          {"origin": [-8,7.515,-8],"size": [16,0.167,2.91]},
          {"origin": [-8,7.682,-8],"size": [16,0.167,1.908]},
          {"origin": [-8,7.849,-8],"size": [16,0.167,0.906]}
          ]
        }
      ]
    }
  ]
}